bb_clients/__init__.py
bb_clients/fc/__init__.py
bb_clients/ims/__init__.py
bb_clients-0.1.38.dist-info/LICENSE
bb_clients-0.1.38.dist-info/WHEEL
bb_clients-0.1.38.dist-info/METADATA
bb_clients-0.1.38.dist-info/RECORD
