Metadata-Version: 2.1
Name: bb_clients
Version: 0.1.38
Summary: Simple python clients for the Gravitate BestBuy Services
Author: James Vogel
Author-email: jim.m.vogel@gmail.com
Requires-Python: >=3.5
Classifier: License :: OSI Approved :: MIT License
Requires-Dist: loguru
Requires-Dist: python-dateutil
Requires-Dist: tenacity
Requires-Dist: sparkles
Requires-Dist: pydantic
Requires-Dist: httpx
Requires-Dist: pytz
Requires-Dist: pytest-watch ; extra == "dev"
Requires-Dist: tomlkit ; extra == "dev"
Requires-Dist: black ; extra == "dev"
Requires-Dist: pytest ; extra == "test"
Requires-Dist: pytest-cov ; extra == "test"
Provides-Extra: dev
Provides-Extra: test
